setup.cfg
setup.py
drf_mockable/__init__.py
drf_mockable/mockable.py
drf_mockable/tests.py
drf_mockable.egg-info/PKG-INFO
drf_mockable.egg-info/SOURCES.txt
drf_mockable.egg-info/dependency_links.txt
drf_mockable.egg-info/not-zip-safe
drf_mockable.egg-info/requires.txt
drf_mockable.egg-info/top_level.txt