Metadata-Version: 1.1
Name: drf-mockable
Version: 0.0.3
Summary: This package makes building mockable APIs a breeze for Django developers.
Home-page: https://github.com/arpan29/drf-mockable
Author: Arpan Gupta
Author-email: arpan29@gmail.com
License: MIT
Download-URL: https://github.com/arpan29/drf-mockable/archive/master.zip
Keywords: mock,DRF,mockable,APIs,REST,Django
Platform: UNKNOWN
